{
    "required": true,
    "package": "io.github.opencubicchunks.cubicchunks.mixin.levelgen",
    "refmap": "CubicChunks-refmap.json",
    "compatibilityLevel": "JAVA_16",
    "minVersion": "0.8",
    "injectors": {
        "defaultRequire": 1
    },
    "overwrites": {
        "conformVisibility": true
    },
    "mixins": [
        "common.biome.MixinBiome",
        "common.biome.MixinBiomeDefaultFeatures",
        "common.biome.MixinFuzzyOffsetConstantColumnBiomeZoomer",
        "common.biome.MixinMultiNoiseBiomeSource",
        "common.carver.MixinWorldCarver",
        "common.feature.MixinBlockBlobFeature",
        "common.feature.MixinCocoaDecorator",
        "common.feature.MixinDecoratedFeature",
        "common.feature.MixinDesertWellFeature",
        "common.feature.MixinFossilFeature",
        "common.feature.MixinIcebergFeature",
        "common.feature.MixinIcePatchFeature",
        "common.feature.MixinIceSpikeFeature",
        "common.feature.MixinLakeFeature",
        "common.feature.MixinSpringFeature",
        "common.feature.nether.MixinBasaltPillarFeature",
        "common.feature.nether.MixinHugeFungusFeature",
        "common.feature.nether.MixinReplaceBlobsFeature",
        "common.feature.nether.MixinTwistyVinesFeature",
        "common.feature.range.MixinRandomPatchFeature",
        "common.MixinBeardifier",
        "common.MixinBlendedNoise",
        "common.MixinChunkGenerator",
        "common.MixinDepthBasedReplacingBaseStoneSource",
        "common.MixinNoiseBasedChunkGenerator",
        "common.MixinNoiseSampler",
        "common.placement.MixinBiasedToBottomHeight",
        "common.placement.MixinCountMultiLayerDecorator",
        "common.placement.MixinDarkOakTreePlacementDecorator",
        "common.placement.MixinDecorationContext",
        "common.placement.MixinHeightMapDecorator",
        "common.placement.MixinHeightMapDoubleDecorator",
        "common.placement.MixinHeightProvider",
        "common.placement.MixinRangeDecorator",
        "common.placement.MixinTrapezoidHeightProvider",
        "common.placement.MixinUniformHeightProvider",
        "common.placement.MixinVerticalDecorator",
        "common.placement.verticalanchor.MixinVerticalAnchorAboveBottom",
        "common.placement.verticalanchor.MixinVerticalAnchorBelowTop",
        "common.structure.MixinStructureFeature",
        "common.structure.MixinStructureFeatureManager",
        "common.structure.MixinStructurePiece",
        "common.structure.MixinStructureStart",
        "common.structure.pieces.MixinOceanRuinPieces",
        "common.surfacebuilder.MixinNetherCappedSurfaceBuilder",
        "common.surfacebuilder.MixinNetherForestSurfaceBuilder",
        "common.surfacebuilder.MixinNetherSurfaceBuilder"
    ],
    "client": [],
    "server": []
}